src_ie_tools/__init__.py
src_ie_tools/announcement_handling.py
src_ie_tools/date_handling.py
src_ie_tools/effective_volumes.py
src_ie_tools/factor_mapping.py
src_ie_tools/forecast_flows_handling.py
src_ie_tools/name_handling.py
src_ie_tools/search_handling.py
src_ie_tools/tracking_assumptions.py
src_ie_tools/user_handling.py
src_ie_tools-0.0.0.0.1.dist-info/LICENSE
src_ie_tools-0.0.0.0.1.dist-info/METADATA
src_ie_tools-0.0.0.0.1.dist-info/WHEEL
src_ie_tools-0.0.0.0.1.dist-info/top_level.txt
src_ie_tools-0.0.0.0.1.dist-info/RECORD
