Metadata-Version: 2.1
Name: src-ie-tools
Version: 0.0.0.0.1
Summary: A higher level of abstraction around API Endpoints.
Author: Samson Rock Capital
Author-email: src.indexdevs@samsonrock.com
License: MIT
License-File: LICENSE
Requires-Dist: numpy
Requires-Dist: pandas
Requires-Dist: requests
